odoo/addons/l10n_it_intrastat_statement/README.rst
odoo/addons/l10n_it_intrastat_statement/__init__.py
odoo/addons/l10n_it_intrastat_statement/__manifest__.py
odoo/addons/l10n_it_intrastat_statement/data/sequence.xml
odoo/addons/l10n_it_intrastat_statement/i18n/es.po
odoo/addons/l10n_it_intrastat_statement/i18n/it.po
odoo/addons/l10n_it_intrastat_statement/i18n/l10n_it_intrastat_statement.pot
odoo/addons/l10n_it_intrastat_statement/migrations/13.0.1.0.0/noupdate_changes.xml
odoo/addons/l10n_it_intrastat_statement/migrations/13.0.1.0.0/post-migration.py
odoo/addons/l10n_it_intrastat_statement/migrations/13.0.1.0.0/pre-migration.py
odoo/addons/l10n_it_intrastat_statement/models/__init__.py
odoo/addons/l10n_it_intrastat_statement/models/account.py
odoo/addons/l10n_it_intrastat_statement/models/config.py
odoo/addons/l10n_it_intrastat_statement/models/intrastat_statement.py
odoo/addons/l10n_it_intrastat_statement/models/intrastat_statement_purchase_section.py
odoo/addons/l10n_it_intrastat_statement/models/intrastat_statement_purchase_section1.py
odoo/addons/l10n_it_intrastat_statement/models/intrastat_statement_purchase_section2.py
odoo/addons/l10n_it_intrastat_statement/models/intrastat_statement_purchase_section3.py
odoo/addons/l10n_it_intrastat_statement/models/intrastat_statement_purchase_section4.py
odoo/addons/l10n_it_intrastat_statement/models/intrastat_statement_sale_section.py
odoo/addons/l10n_it_intrastat_statement/models/intrastat_statement_sale_section1.py
odoo/addons/l10n_it_intrastat_statement/models/intrastat_statement_sale_section2.py
odoo/addons/l10n_it_intrastat_statement/models/intrastat_statement_sale_section3.py
odoo/addons/l10n_it_intrastat_statement/models/intrastat_statement_sale_section4.py
odoo/addons/l10n_it_intrastat_statement/models/intrastat_statement_section.py
odoo/addons/l10n_it_intrastat_statement/readme/CONTRIBUTORS.rst
odoo/addons/l10n_it_intrastat_statement/readme/DESCRIPTION.rst
odoo14_addon_l10n_it_intrastat_statement-14.0.1.5.1.dist-info/METADATA
odoo14_addon_l10n_it_intrastat_statement-14.0.1.5.1.dist-info/WHEEL
odoo14_addon_l10n_it_intrastat_statement-14.0.1.5.1.dist-info/top_level.txt
odoo14_addon_l10n_it_intrastat_statement-14.0.1.5.1.dist-info/RECORD
