Metadata-Version: 2.1
Name: odoo14-addon-l10n_it_intrastat_statement
Version: 14.0.1.5.1
Summary: Dichiarazione Intrastat per l'Agenzia delle Dogane
Home-page: https://github.com/OCA/l10n-italy
Author: Openforce, Link IT srl, Agile Business Group, Odoo Community Association (OCA)
Author-email: support@odoo-community.org
License: AGPL-3
Classifier: Programming Language :: Python
Classifier: Framework :: Odoo
Classifier: Framework :: Odoo :: 14.0
Classifier: License :: OSI Approved :: GNU Affero General Public License v3
Requires-Python: >=3.6
Requires-Dist: odoo14-addon-l10n-it-intrastat
Requires-Dist: odoo<14.1dev,>=14.0a
